odoo/addons/frappe_etax_service/README.rst
odoo/addons/frappe_etax_service/__init__.py
odoo/addons/frappe_etax_service/__manifest__.py
odoo/addons/frappe_etax_service/data/cron.xml
odoo/addons/frappe_etax_service/data/purpose_code_data.xml
odoo/addons/frappe_etax_service/data/server_action.xml
odoo/addons/frappe_etax_service/i18n/frappe_etax_service.pot
odoo/addons/frappe_etax_service/inet/__init__.py
odoo/addons/frappe_etax_service/inet/inet_data_template.py
odoo/addons/frappe_etax_service/models/__init__.py
odoo/addons/frappe_etax_service/models/account_move.py
odoo/addons/frappe_etax_service/models/account_payment.py
odoo/addons/frappe_etax_service/models/doctype.py
odoo/addons/frappe_etax_service/models/etax_th.py
odoo/addons/frappe_etax_service/models/purpose_code.py
odoo/addons/frappe_etax_service/models/res_config_settings.py
odoo/addons/frappe_etax_service/readme/CONFIGURE.rst
odoo/addons/frappe_etax_service/readme/CONTRIBUTORS.rst
odoo/addons/frappe_etax_service/readme/DESCRIPTION.rst
odoo/addons/frappe_etax_service/security/ir.model.access.csv
odoo/addons/frappe_etax_service/static/description/icon.png
odoo/addons/frappe_etax_service/static/description/index.html
odoo/addons/frappe_etax_service/views/account_move_views.xml
odoo/addons/frappe_etax_service/views/account_payment_views.xml
odoo/addons/frappe_etax_service/views/doctype_views.xml
odoo/addons/frappe_etax_service/views/purpose_code_views.xml
odoo/addons/frappe_etax_service/views/res_config_settings.xml
odoo/addons/frappe_etax_service/wizards/__init__.py
odoo/addons/frappe_etax_service/wizards/account_debit_note.py
odoo/addons/frappe_etax_service/wizards/account_debit_note_view.xml
odoo/addons/frappe_etax_service/wizards/account_move_reversal.py
odoo/addons/frappe_etax_service/wizards/account_move_reversal_view.xml
odoo/addons/frappe_etax_service/wizards/wizard_select_etax_doctype.py
odoo/addons/frappe_etax_service/wizards/wizard_select_etax_doctype_view.xml
odoo_addon_frappe_etax_service-15.0.1.0.1.dist-info/METADATA
odoo_addon_frappe_etax_service-15.0.1.0.1.dist-info/WHEEL
odoo_addon_frappe_etax_service-15.0.1.0.1.dist-info/top_level.txt
odoo_addon_frappe_etax_service-15.0.1.0.1.dist-info/RECORD
