Metadata-Version: 2.1
Name: odoo-addon-frappe_etax_service
Version: 15.0.1.0.1
Requires-Python: >=3.8
Requires-Dist: odoo-addon-l10n_th_account_tax>=15.0dev,<15.1dev
Requires-Dist: odoo>=15.0a,<15.1dev
Summary: Connector to Frappe eTax service
Home-page: https://github.com/ecosoft-odoo/ecosoft-addons
License: AGPL-3
Author: Kitti U., Ecosoft
Classifier: Programming Language :: Python
Classifier: Framework :: Odoo
Classifier: Framework :: Odoo :: 15.0
Classifier: License :: OSI Approved :: GNU Affero General Public License v3
